elemental_core/__init__.py
elemental_core/_elemental_base.py
elemental_core/_elemental_error.py
elemental_core/_hook.py
elemental_core/_no_value.py
elemental_core/util.py
elemental_core-0.2.1.dev0.dist-info/DESCRIPTION.rst
elemental_core-0.2.1.dev0.dist-info/METADATA
elemental_core-0.2.1.dev0.dist-info/RECORD
elemental_core-0.2.1.dev0.dist-info/WHEEL
elemental_core-0.2.1.dev0.dist-info/metadata.json
elemental_core-0.2.1.dev0.dist-info/top_level.txt
