Metadata-Version: 2.0
Name: elemental-core
Version: 0.2.1.dev0
Summary: Functionality shared across Elemental CMS.
Home-page: https://github.com/artPlusPlus/elemental-core
Author: Matt Robinson
Author-email: matt@technicalartisan.com
License: Mozilla Public License 2.0 (MPL 2.0)
Keywords: elemental cms core
Platform: UNKNOWN
Classifier: Development Status :: 1 - Planning
Classifier: License :: OSI Approved :: Mozilla Public License 2.0 (MPL 2.0)
Classifier: Intended Audience :: Developers
Classifier: Environment :: Web Environment
Classifier: Programming Language :: Python
Classifier: Programming Language :: Python :: 3
Classifier: Topic :: Internet :: WWW/HTTP :: Dynamic Content
Classifier: Topic :: Software Development :: Libraries :: Python Modules
Provides-Extra: doc
Requires-Dist: sphinx (>=1.3.0); extra == 'doc'
Provides-Extra: test
Requires-Dist: pytest; extra == 'test'
